vauban/__init__.py
vauban/api.py
vauban/cli.py
vauban/config.py
vauban/engine.py
vauban/entry.py
vauban/formatting.py
vauban/history.py
vauban/intel.py
vauban/interfaces.py
vauban/judge.py
vauban/llm.py
vauban/personas.py
vauban/prompts.py
vauban/py.typed
vauban/report.py
vauban/scenarios.py
vauban/target.py
vauban/tools.py
vauban/tracing.py
vauban/viz.py
vauban/strategies/base.py
vauban/strategies/many_shot.py
vauban-0.1.2.dist-info/licenses/LICENSE
vauban-0.1.2.dist-info/METADATA
vauban-0.1.2.dist-info/WHEEL
vauban-0.1.2.dist-info/entry_points.txt
vauban-0.1.2.dist-info/top_level.txt
vauban-0.1.2.dist-info/RECORD
