Metadata-Version: 2.4
Name: vauban
Version: 0.1.2
Summary: Add your description here
Requires-Python: >=3.12
License-File: LICENSE
Requires-Dist: lancedb
Requires-Dist: scikit-learn
Requires-Dist: openai
Requires-Dist: weave
Requires-Dist: numpy
Requires-Dist: embedding-atlas
Requires-Dist: anywidget
Requires-Dist: pandas
Requires-Dist: pytest>=9.0.1
Requires-Dist: python-dotenv>=1.2.1
Requires-Dist: rich>=14.2.0
Provides-Extra: dev
Requires-Dist: pytest; extra == "dev"
Requires-Dist: pytest-asyncio; extra == "dev"
Dynamic: license-file
